carrotlite/__init__.py
carrotlite/_version.py
carrotlite/clilite/__init__.py
carrotlite/clilite/clilite.py
carrotlite/clilite/subcommands/__init__.py
carrotlite/clilite/subcommands/run.py
carrotlite/tools/__init__.py
carrotlite/tools/file_helpers.py
carrotlite/tools/mappingrules.py
carrotlite/tools/metrics.py
carrotlite/tools/omopcdm.py
carrotlite_PhilAppleby-0.0.1.dist-info/LICENSE
carrotlite_PhilAppleby-0.0.1.dist-info/METADATA
carrotlite_PhilAppleby-0.0.1.dist-info/WHEEL
carrotlite_PhilAppleby-0.0.1.dist-info/top_level.txt
carrotlite_PhilAppleby-0.0.1.dist-info/RECORD
