Metadata-Version: 2.1
Name: carrotlite_PhilAppleby
Version: 0.0.1
Summary: Carrotlite early example
Home-page: https://github.com/HDRUK/CaRROT-CDM-Lite
Author-email: PD Appleby <pdappleby@gmail.com>
Project-URL: Homepage, https://github.com/pypa/sampleproject
Project-URL: Issues, https://github.com/pypa/sampleproject/issues
Classifier: Programming Language :: Python :: 3
Classifier: License :: OSI Approved :: MIT License
Classifier: Operating System :: OS Independent
Requires-Python: >=3.6
License-File: LICENSE
